detech_dynamo_pkg/__init__.py
detech_dynamo_pkg/dynamodb_functions.py
detech_dynamo_pkg/utils/__init__.py
detech_dynamo_pkg/utils/dynamo_utils.py
detech_query_pkg/__init__.py
detech_query_pkg/dynamodb.py
detech_query_pkg/dynamodb_queries.py
detech_query_pkg/utils/__init__.py
detech_query_pkg/utils/dynamodb_utils.py
functions/__init__.py
functions/dynamodb_functions.py
functions/utils/__init__.py
functions/utils/dynamo_utils.py
utils/__init__.py
utils/dynamo_utils.py
dynamodb_detech_ai-0.0.24.dist-info/LICENSE
dynamodb_detech_ai-0.0.24.dist-info/METADATA
dynamodb_detech_ai-0.0.24.dist-info/WHEEL
dynamodb_detech_ai-0.0.24.dist-info/top_level.txt
dynamodb_detech_ai-0.0.24.dist-info/RECORD
