Metadata-Version: 2.1
Name: dynamodb-detech-ai
Version: 0.0.24
Summary: DynamoDB utils
Home-page: https://github.com/detech-ai/Data_Pipelines
Author: Example Author
Author-email: j.velez2210@gmail.com
License: UNKNOWN
Platform: UNKNOWN
Classifier: Programming Language :: Python :: 3
Classifier: License :: OSI Approved :: MIT License
Classifier: Operating System :: OS Independent
Requires-Python: >=3.6
